MANIFEST.in
README.md
setup.py
pytreebank/__init__.py
pytreebank/box_office.py
pytreebank/download.py
pytreebank/labeled_trees.py
pytreebank/parse.py
pytreebank/treelstm.py
pytreebank/utils.py
pytreebank.egg-info/PKG-INFO
pytreebank.egg-info/SOURCES.txt
pytreebank.egg-info/dependency_links.txt
pytreebank.egg-info/not-zip-safe
pytreebank.egg-info/top_level.txt
pytreebank/javascript/__init__.py
pytreebank/javascript/c3.min.js
pytreebank/javascript/d3.min.js
pytreebank/javascript/sentree.min.js
pytreebank/javascript/sentrees.min.js
pytreebank/javascript/tree_visualization.css
pytreebank/javascript/tree_visualization.js