Metadata-Version: 1.1
Name: pytreebank
Version: 0.2.4
Summary: Python package for loading Stanford Sentiment Treebank corpus
Home-page: https://github.com/JonathanRaiman/pytreebank
Author: Jonathan Raiman
Author-email: jonathanraiman@gmail.com
License: MIT
Download-URL: https://github.com/JonathanRaiman/pytreebank
Keywords: Machine Learning,NLP
Platform: any
Classifier: Intended Audience :: Science/Research
Classifier: Operating System :: OS Independent
Classifier: Programming Language :: Python :: 3.3
Classifier: Programming Language :: Python :: 2.7
Classifier: Topic :: Text Processing :: Linguistic
